Metadata-Version: 2.1
Name: pylib3
Version: 0.0.4
Summary: Python Shared Library
Home-page: https://gitlab.com/shlomi.ben.david/pylib3
Author: Shlomi Ben-David
Author-email: shlomi.ben.david@gmail.com
Classifier: Programming Language :: Python :: 2.7
Classifier: Programming Language :: Python :: 3
Classifier: License :: OSI Approved :: MIT License
Classifier: Operating System :: OS Independent
Requires-Python: >=2.7
License-File: LICENSE
